README.rst
setup.py
fifemon/__init__.py
fifemon/graphite.py
fifemon/influx.py
fifemon/probe.py
fifemon_probes_common.egg-info/PKG-INFO
fifemon_probes_common.egg-info/SOURCES.txt
fifemon_probes_common.egg-info/dependency_links.txt
fifemon_probes_common.egg-info/requires.txt
fifemon_probes_common.egg-info/top_level.txt